OLT_ONT_PORTFINDER/__init__.py
OLT_ONT_PORTFINDER/ont_12ports.py
OLT_ONT_PORTFINDER/ont_16ports.py
OLT_ONT_PORTFINDER/ont_20ports_R.py
OLT_ONT_PORTFINDER/ont_20ports_l.py
OLT_ONT_PORTFINDER/ont_24ports.py
OLT_ONT_PORTFINDER/ont_4ports.py
OLT_ONT_PORTFINDER/ont_8ports.py
OLT_ONT_PORTFINDER/portfinder.py
OLT_ONT_PORTFINDER/tests.py
nokia_ont_port_finder-0.0.12.dist-info/METADATA
nokia_ont_port_finder-0.0.12.dist-info/WHEEL
nokia_ont_port_finder-0.0.12.dist-info/top_level.txt
nokia_ont_port_finder-0.0.12.dist-info/RECORD
