Metadata-Version: 2.1
Name: nokia_ont_port_finder
Version: 0.0.12
Summary: Network Automation and Programmability Abstraction Layer for NOKIA OLT and ONT DYNAMIC HARDWARE DETECTION
Home-page: 
Author: David Johnnes
Author-email: david.johnnes@gmail.com
Keywords: NOKIA ONT DYNAMIC PORT FINDER,DYNAMIC HARDWARE DETECTION
Classifier: Topic :: Utilities
Classifier: Programming Language :: Python :: 3
Classifier: Operating System :: OS Independent
Classifier: License :: OSI Approved :: BSD License
Requires-Dist: sshFRIEND
